junit_xml_output/__init__.py
junit_xml_output/test.py
junit_xml_output-2.0.0.dist-info/AUTHORS
junit_xml_output-2.0.0.dist-info/LICENSE
junit_xml_output-2.0.0.dist-info/METADATA
junit_xml_output-2.0.0.dist-info/WHEEL
junit_xml_output-2.0.0.dist-info/pbr.json
junit_xml_output-2.0.0.dist-info/top_level.txt
junit_xml_output-2.0.0.dist-info/RECORD
